simple_file_repository/__init__.py
simple_file_repository/exceptions.py
simple_file_repository/filestorage.py
simple_file_repository/photostorage.py
simple_file_repository/photostorages.py
simple_file_repository/s3storage.py
simple_file_repository/storage.py
simple_file_repository/utils.py
simple_file_repository-0.11.0.dist-info/LICENSE
simple_file_repository-0.11.0.dist-info/METADATA
simple_file_repository-0.11.0.dist-info/WHEEL
simple_file_repository-0.11.0.dist-info/RECORD
