Metadata-Version: 2.1
Name: simple-file-repository
Version: 0.11.0
Summary: A simple file and photo repository.
License: MIT
Author: theirix
Author-email: theirix@gmail.com
Requires-Python: >=3.9,<3.13
Classifier: Development Status :: 4 - Beta
Classifier: License :: OSI Approved :: MIT License
Classifier: Programming Language :: Python
Classifier: Programming Language :: Python :: 3
Classifier: Programming Language :: Python :: 3.9
Classifier: Programming Language :: Python :: 3.10
Classifier: Programming Language :: Python :: 3.11
Classifier: Programming Language :: Python :: 3.12
Requires-Dist: boto3 (>=1,<2)
Requires-Dist: filemagic (>=1.6,<2.0)
Requires-Dist: requests (>=2,<3)
